Relogio24h/contadorbcd.sv
module ContadorBCD(q,clk,reset);
    output reg [3:0] q;
    input clk;
    input reset;

    initial
        q <= 4'b0000;

    always @(posedge clk, posedge reset) begin
        if(!reset)
            if (q >= 4'b1001)
            begin
                q <= 4'b0000;
            end
            else
                q <= q + 1;
        else
            q <= 4'b0000;
    end

endmodule

Relogio24h/testbench.sv
module test;

    reg  mainclk, genreset;
    wire [3:0] dhourq; //dezena de horas
    wire [3:0] uhourq; //unidade de horas
    wire [3:0] dminq; //dezena de minutos
    wire [3:0] uminq; //unidade de minutos

    /** Sinais de reset*/
    wire dhour_rst, uhour_rst, dmin_rst, umin_rst;

    /** Sinais de clock*/
    wire dmin_clk, uhour_clk, dhour_clk; //clock dos contadores em cascata.

    /** Sinal de reset geral*/
    wire sysreset, turnday;

    assign dhour_rst  = (sysreset || (dhourq > 4'b0010));
    assign dmin_rst = (sysreset || (dminq > 4'b0101));
    assign uhour_rst = sysreset /*|| ((dhourq > 4'b0001) && (uhourq > 4'b0100)))*/;
    assign umin_rst = sysreset;

    assign dmin_clk = ~(uminq >= 4'b1001);
    assign dhour_clk = ~(uhourq >= 4'b1001);
    assign uhour_clk = ~(dmin_rst ^ sysreset);
    assign turnday = (dhourq >= 4'b0010) && (uhourq >= 4'b0100);
    assign sysreset = turnday || genreset;

    initial
    begin
        #90000 $finish;
    end

    ContadorBCD HOUR_DEC(
        .q(dhourq),
        .clk(dhour_clk),
        .reset(dhour_rst)
    );

    ContadorBCD HOUR_UNIT(
        .q(uhourq),
        .clk(uhour_clk),
        .reset(uhour_rst)
    );

    ContadorBCD MIN_DEC(
        .q(dminq),
        .clk(dmin_clk),
        .reset(dmin_rst)
    );

    ContadorBCD MIN_UNIT(
        .q(uminq),
        .clk(mainclk),
        .reset(umin_rst)
    );

    initial begin
        $dumpfile("dump.vcd");
        $dumpvars(1,test);

        mainclk = 0;
        genreset = 0;
        reset;

        //#130 reset;

    end

    always
    begin
        #30 mainclk = ~mainclk;
        #30 mainclk = ~mainclk;
    end

    task reset;
        begin
            #1 genreset = ~genreset;
            #1 genreset = ~genreset;
        end
    endtask

endmodule

Relogio24h/dump.vcd
$date
	Tue Mar 17 23:22:22 2020
$end
$version
	Icarus Verilog
$end
$timescale
	1s
$end
$scope module test $end
$var wire 1 ! dhour_clk $end
$var wire 1 " dhour_rst $end
$var wire 1 # dmin_clk $end
$var wire 1 $ dmin_rst $end
$var wire 1 % sysreset $end
$var wire 1 & turnday $end
$var wire 1 ' uhour_clk $end
$var wire 1 ( uhour_rst $end
$var wire 1 ) umin_rst $end
$var wire 4 * uminq [3:0] $end
$var wire 4 + uhourq [3:0] $end
$var wire 4 , dminq [3:0] $end
$var wire 4 - dhourq [3:0] $end
$var reg 1 . genreset $end
$var reg 1 / mainclk $end
$upscope $end
$enddefinitions $end
#0
$dumpvars
0/
0.
b0 -
b0 ,
b1 +
b0 *
0)
0(
1'
0&
0%
0$
1#
0"
1!
$end
#1
b0 +
1$
1"
1)
1(
1%
1.
#2
0$
0"
0)
0(
0%
0.
#30
b1 *
1/
#60
0/
#90
b10 *
1/
#120
0/
#150
b11 *
1/
#180
0/
#210
b100 *
1/
#240
0/
#270
b101 *
1/
#300
0/
#330
b110 *
1/
#360
0/
#390
b111 *
1/
#420
0/
#450
b1000 *
1/
#480
0/
#510
0#
b1001 *
1/
#540
0/
#570
b1 ,
1#
b0 *
1/
#600
0/
#630
b1 *
1/
#660
0/
#690
b10 *
1/
#720
0/
#750
b11 *
1/
#780
0/
#810
b100 *
1/
#840
0/
#870
b101 *
1/
#900
0/
#930
b110 *
1/
#960
0/
#990
b111 *
1/
#1020
0/
#1050
b1000 *
1/
#1080
0/
#1110
0#
b1001 *
1/
#1140
0/
#1170
b10 ,
1#
b0 *
1/
#1200
0/
#1230
b1 *
1/
#1260
0/
#1290
b10 *
1/
#1320
0/
#1350
b11 *
1/
#1380
0/
#1410
b100 *
1/
#1440
0/
#1470
b101 *
1/
#1500
0/
#1530
b110 *
1/
#1560
0/
#1590
b111 *
1/
#1620
0/
#1650
b1000 *
1/
#1680
0/
#1710
0#
b1001 *
1/
#1740
0/
#1770
b11 ,
1#
b0 *
1/
#1800
0/
#1830
b1 *
1/
#1860
0/
#1890
b10 *
1/
#1920
0/
#1950
b11 *
1/
#1980
0/
#2010
b100 *
1/
#2040
0/
#2070
b101 *
1/
#2100
0/
#2130
b110 *
1/
#2160
0/
#2190
b111 *
1/
#2220
0/
#2250
b1000 *
1/
#2280
0/
#2310
0#
b1001 *
1/
#2340
0/
#2370
b100 ,
1#
b0 *
1/
#2400
0/
#2430
b1 *
1/
#2460
0/
#2490
b10 *
1/
#2520
0/
#2550
b11 *
1/
#2580
0/
#2610
b100 *
1/
#2640
0/
#2670
b101 *
1/
#2700
0/
#2730
b110 *
1/
#2760
0/
#2790
b111 *
1/
#2820
0/
#2850
b1000 *
1/
#2880
0/
#2910
0#
b1001 *
1/
#2940
0/
#2970
b101 ,
1#
b0 *
1/
#3000
0/
#3030
b1 *
1/
#3060
0/
#3090
b10 *
1/
#3120
0/
#3150
b11 *
1/
#3180
0/
#3210
b100 *
1/
#3240
0/
#3270
b101 *
1/
#3300
0/
#3330
b110 *
1/
#3360
0/
#3390
b111 *
1/
#3420
0/
#3450
b1000 *
1/
#3480
0/
#3510
0#
b1001 *
1/
#3540
0/
#3570
b1 +
1'
0$
b0 ,
1#
b0 *
1/
#3600
0/
#3630
b1 *
1/
#3660
0/
#3690
b10 *
1/
#3720
0/
#3750
b11 *
1/
#3780
0/
#3810
b100 *
1/
#3840
0/
#3870
b101 *
1/
#3900
0/
#3930
b110 *
1/
#3960
0/
#3990
b111 *
1/
#4020
0/
#4050
b1000 *
1/
#4080
0/
#4110
0#
b1001 *
1/
#4140
0/
#4170
b1 ,
1#
b0 *
1/
#4200
0/
#4230
b1 *
1/
#4260
0/
#4290
b10 *
1/
#4320
0/
#4350
b11 *
1/
#4380
0/
#4410
b100 *
1/
#4440
0/
#4470
b101 *
1/
#4500
0/
#4530
b110 *
1/
#4560
0/
#4590
b111 *
1/
#4620
0/
#4650
b1000 *
1/
#4680
0/
#4710
0#
b1001 *
1/
#4740
0/
#4770
b10 ,
1#
b0 *
1/
#4800
0/
#4830
b1 *
1/
#4860
0/
#4890
b10 *
1/
#4920
0/
#4950
b11 *
1/
#4980
0/
#5010
b100 *
1/
#5040
0/
#5070
b101 *
1/
#5100
0/
#5130
b110 *
1/
#5160
0/
#5190
b111 *
1/
#5220
0/
#5250
b1000 *
1/
#5280
0/
#5310
0#
b1001 *
1/
#5340
0/
#5370
b11 ,
1#
b0 *
1/
#5400
0/
#5430
b1 *
1/
#5460
0/
#5490
b10 *
1/
#5520
0/
#5550
b11 *
1/
#5580
0/
#5610
b100 *
1/
#5640
0/
#5670
b101 *
1/
#5700
0/
#5730
b110 *
1/
#5760
0/
#5790
b111 *
1/
#5820
0/
#5850
b1000 *
1/
#5880
0/
#5910
0#
b1001 *
1/
#5940
0/
#5970
b100 ,
1#
b0 *
1/
#6000
0/
#6030
b1 *
1/
#6060
0/
#6090
b10 *
1/
#6120
0/
#6150
b11 *
1/
#6180
0/
#6210
b100 *
1/
#6240
0/
#6270
b101 *
1/
#6300
0/
#6330
b110 *
1/
#6360
0/
#6390
b111 *
1/
#6420
0/
#6450
b1000 *
1/
#6480
0/
#6510
0#
b1001 *
1/
#6540
0/
#6570
b101 ,
1#
b0 *
1/
#6600
0/
#6630
b1 *
1/
#6660
0/
#6690
b10 *
1/
#6720
0/
#6750
b11 *
1/
#6780
0/
#6810
b100 *
1/
#6840
0/
#6870
b101 *
1/
#6900
0/
#6930
b110 *
1/
#6960
0/
#6990
b111 *
1/
#7020
0/
#7050
b1000 *
1/
#7080
0/
#7110
0#
b1001 *
1/
#7140
0/
#7170
b10 +
1'
0$
b0 ,
1#
b0 *
1/
#7200
0/
#7230
b1 *
1/
#7260
0/
#7290
b10 *
1/
#7320
0/
#7350
b11 *
1/
#7380
0/
#7410
b100 *
1/
#7440
0/
#7470
b101 *
1/
#7500
0/
#7530
b110 *
1/
#7560
0/
#7590
b111 *
1/
#7620
0/
#7650
b1000 *
1/
#7680
0/
#7710
0#
b1001 *
1/
#7740
0/
#7770
b1 ,
1#
b0 *
1/
#7800
0/
#7830
b1 *
1/
#7860
0/
#7890
b10 *
1/
#7920
0/
#7950
b11 *
1/
#7980
0/
#8010
b100 *
1/
#8040
0/
#8070
b101 *
1/
#8100
0/
#8130
b110 *
1/
#8160
0/
#8190
b111 *
1/
#8220
0/
#8250
b1000 *
1/
#8280
0/
#8310
0#
b1001 *
1/
#8340
0/
#8370
b10 ,
1#
b0 *
1/
#8400
0/
#8430
b1 *
1/
#8460
0/
#8490
b10 *
1/
#8520
0/
#8550
b11 *
1/
#8580
0/
#8610
b100 *
1/
#8640
0/
#8670
b101 *
1/
#8700
0/
#8730
b110 *
1/
#8760
0/
#8790
b111 *
1/
#8820
0/
#8850
b1000 *
1/
#8880
0/
#8910
0#
b1001 *
1/
#8940
0/
#8970
b11 ,
1#
b0 *
1/
#9000
0/
#9030
b1 *
1/
#9060
0/
#9090
b10 *
1/
#9120
0/
#9150
b11 *
1/
#9180
0/
#9210
b100 *
1/
#9240
0/
#9270
b101 *
1/
#9300
0/
#9330
b110 *
1/
#9360
0/
#9390
b111 *
1/
#9420
0/
#9450
b1000 *
1/
#9480
0/
#9510
0#
b1001 *
1/
#9540
0/
#9570
b100 ,
1#
b0 *
1/
#9600
0/
#9630
b1 *
1/
#9660
0/
#9690
b10 *
1/
#9720
0/
#9750
b11 *
1/
#9780
0/
#9810
b100 *
1/
#9840
0/
#9870
b101 *
1/
#9900
0/
#9930
b110 *
1/
#9960
0/
#9990
b111 *
1/
#10020
0/
#10050
b1000 *
1/
#10080
0/
#10110
0#
b1001 *
1/
#10140
0/
#10170
b101 ,
1#
b0 *
1/
#10200
0/
#10230
b1 *
1/
#10260
0/
#10290
b10 *
1/
#10320
0/
#10350
b11 *
1/
#10380
0/
#10410
b100 *
1/
#10440
0/
#10470
b101 *
1/
#10500
0/
#10530
b110 *
1/
#10560
0/
#10590
b111 *
1/
#10620
0/
#10650
b1000 *
1/
#10680
0/
#10710
0#
b1001 *
1/
#10740
0/
#10770
b11 +
1'
0$
b0 ,
1#
b0 *
1/
#10800
0/
#10830
b1 *
1/
#10860
0/
#10890
b10 *
1/
#10920
0/
#10950
b11 *
1/
#10980
0/
#11010
b100 *
1/
#11040
0/
#11070
b101 *
1/
#11100
0/
#11130
b110 *
1/
#11160
0/
#11190
b111 *
1/
#11220
0/
#11250
b1000 *
1/
#11280
0/
#11310
0#
b1001 *
1/
#11340
0/
#11370
b1 ,
1#
b0 *
1/
#11400
0/
#11430
b1 *
1/
#11460
0/
#11490
b10 *
1/
#11520
0/
#11550
b11 *
1/
#11580
0/
#11610
b100 *
1/
#11640
0/
#11670
b101 *
1/
#11700
0/
#11730
b110 *
1/
#11760
0/
#11790
b111 *
1/
#11820
0/
#11850
b1000 *
1/
#11880
0/
#11910
0#
b1001 *
1/
#11940
0/
#11970
b10 ,
1#
b0 *
1/
#12000
0/
#12030
b1 *
1/
#12060
0/
#12090
b10 *
1/
#12120
0/
#12150
b11 *
1/
#12180
0/
#12210
b100 *
1/
#12240
0/
#12270
b101 *
1/
#12300
0/
#12330
b110 *
1/
#12360
0/
#12390
b111 *
1/
#12420
0/
#12450
b1000 *
1/
#12480
0/
#12510
0#
b1001 *
1/
#12540
0/
#12570
b11 ,
1#
b0 *
1/
#12600
0/
#12630
b1 *
1/
#12660
0/
#12690
b10 *
1/
#12720
0/
#12750
b11 *
1/
#12780
0/
#12810
b100 *
1/
#12840
0/
#12870
b101 *
1/
#12900
0/
#12930
b110 *
1/
#12960
0/
#12990
b111 *
1/
#13020
0/
#13050
b1000 *
1/
#13080
0/
#13110
0#
b1001 *
1/
#13140
0/
#13170
b100 ,
1#
b0 *
1/
#13200
0/
#13230
b1 *
1/
#13260
0/
#13290
b10 *
1/
#13320
0/
#13350
b11 *
1/
#13380
0/
#13410
b100 *
1/
#13440
0/
#13470
b101 *
1/
#13500
0/
#13530
b110 *
1/
#13560
0/
#13590
b111 *
1/
#13620
0/
#13650
b1000 *
1/
#13680
0/
#13710
0#
b1001 *
1/
#13740
0/
#13770
b101 ,
1#
b0 *
1/
#13800
0/
#13830
b1 *
1/
#13860
0/
#13890
b10 *
1/
#13920
0/
#13950
b11 *
1/
#13980
0/
#14010
b100 *
1/
#14040
0/
#14070
b101 *
1/
#14100
0/
#14130
b110 *
1/
#14160
0/
#14190
b111 *
1/
#14220
0/
#14250
b1000 *
1/
#14280
0/
#14310
0#
b1001 *
1/
#14340
0/
#14370
b100 +
1'
0$
b0 ,
1#
b0 *
1/
#14400
0/
#14430
b1 *
1/
#14460
0/
#14490
b10 *
1/
#14520
0/
#14550
b11 *
1/
#14580
0/
#14610
b100 *
1/
#14640
0/
#14670
b101 *
1/
#14700
0/
#14730
b110 *
1/
#14760
0/
#14790
b111 *
1/
#14820
0/
#14850
b1000 *
1/
#14880
0/
#14910
0#
b1001 *
1/
#14940
0/
#14970
b1 ,
1#
b0 *
1/
#15000
0/
#15030
b1 *
1/
#15060
0/
#15090
b10 *
1/
#15120
0/
#15150
b11 *
1/
#15180
0/
#15210
b100 *
1/
#15240
0/
#15270
b101 *
1/
#15300
0/
#15330
b110 *
1/
#15360
0/
#15390
b111 *
1/
#15420
0/
#15450
b1000 *
1/
#15480
0/
#15510
0#
b1001 *
1/
#15540
0/
#15570
b10 ,
1#
b0 *
1/
#15600
0/
#15630
b1 *
1/
#15660
0/
#15690
b10 *
1/
#15720
0/
#15750
b11 *
1/
#15780
0/
#15810
b100 *
1/
#15840
0/
#15870
b101 *
1/
#15900
0/
#15930
b110 *
1/
#15960
0/
#15990
b111 *
1/
#16020
0/
#16050
b1000 *
1/
#16080
0/
#16110
0#
b1001 *
1/
#16140
0/
#16170
b11 ,
1#
b0 *
1/
#16200
0/
#16230
b1 *
1/
#16260
0/
#16290
b10 *
1/
#16320
0/
#16350
b11 *
1/
#16380
0/
#16410
b100 *
1/
#16440
0/
#16470
b101 *
1/
#16500
0/
#16530
b110 *
1/
#16560
0/
#16590
b111 *
1/
#16620
0/
#16650
b1000 *
1/
#16680
0/
#16710
0#
b1001 *
1/
#16740
0/
#16770
b100 ,
1#
b0 *
1/
#16800
0/
#16830
b1 *
1/
#16860
0/
#16890
b10 *
1/
#16920
0/
#16950
b11 *
1/
#16980
0/
#17010
b100 *
1/
#17040
0/
#17070
b101 *
1/
#17100
0/
#17130
b110 *
1/
#17160
0/
#17190
b111 *
1/
#17220
0/
#17250
b1000 *
1/
#17280
0/
#17310
0#
b1001 *
1/
#17340
0/
#17370
b101 ,
1#
b0 *
1/
#17400
0/
#17430
b1 *
1/
#17460
0/
#17490
b10 *
1/
#17520
0/
#17550
b11 *
1/
#17580
0/
#17610
b100 *
1/
#17640
0/
#17670
b101 *
1/
#17700
0/
#17730
b110 *
1/
#17760
0/
#17790
b111 *
1/
#17820
0/
#17850
b1000 *
1/
#17880
0/
#17910
0#
b1001 *
1/
#17940
0/
#17970
b101 +
1'
0$
b0 ,
1#
b0 *
1/
#18000
0/
#18030
b1 *
1/
#18060
0/
#18090
b10 *
1/
#18120
0/
#18150
b11 *
1/
#18180
0/
#18210
b100 *
1/
#18240
0/
#18270
b101 *
1/
#18300
0/
#18330
b110 *
1/
#18360
0/
#18390
b111 *
1/
#18420
0/
#18450
b1000 *
1/
#18480
0/
#18510
0#
b1001 *
1/
#18540
0/
#18570
b1 ,
1#
b0 *
1/
#18600
0/
#18630
b1 *
1/
#18660
0/
#18690
b10 *
1/
#18720
0/
#18750
b11 *
1/
#18780
0/
#18810
b100 *
1/
#18840
0/
#18870
b101 *
1/
#18900
0/
#18930
b110 *
1/
#18960
0/
#18990
b111 *
1/
#19020
0/
#19050
b1000 *
1/
#19080
0/
#19110
0#
b1001 *
1/
#19140
0/
#19170
b10 ,
1#
b0 *
1/
#19200
0/
#19230
b1 *
1/
#19260
0/
#19290
b10 *
1/
#19320
0/
#19350
b11 *
1/
#19380
0/
#19410
b100 *
1/
#19440
0/
#19470
b101 *
1/
#19500
0/
#19530
b110 *
1/
#19560
0/
#19590
b111 *
1/
#19620
0/
#19650
b1000 *
1/
#19680
0/
#19710
0#
b1001 *
1/
#19740
0/
#19770
b11 ,
1#
b0 *
1/
#19800
0/
#19830
b1 *
1/
#19860
0/
#19890
b10 *
1/
#19920
0/
#19950
b11 *
1/
#19980
0/
#20010
b100 *
1/
#20040
0/
#20070
b101 *
1/
#20100
0/
#20130
b110 *
1/
#20160
0/
#20190
b111 *
1/
#20220
0/
#20250
b1000 *
1/
#20280
0/
#20310
0#
b1001 *
1/
#20340
0/
#20370
b100 ,
1#
b0 *
1/
#20400
0/
#20430
b1 *
1/
#20460
0/
#20490
b10 *
1/
#20520
0/
#20550
b11 *
1/
#20580
0/
#20610
b100 *
1/
#20640
0/
#20670
b101 *
1/
#20700
0/
#20730
b110 *
1/
#20760
0/
#20790
b111 *
1/
#20820
0/
#20850
b1000 *
1/
#20880
0/
#20910
0#
b1001 *
1/
#20940
0/
#20970
b101 ,
1#
b0 *
1/
#21000
0/
#21030
b1 *
1/
#21060
0/
#21090
b10 *
1/
#21120
0/
#21150
b11 *
1/
#21180
0/
#21210
b100 *
1/
#21240
0/
#21270
b101 *
1/
#21300
0/
#21330
b110 *
1/
#21360
0/
#21390
b111 *
1/
#21420
0/
#21450
b1000 *
1/
#21480
0/
#21510
0#
b1001 *
1/
#21540
0/
#21570
b110 +
1'
0$
b0 ,
1#
b0 *
1/
#21600
0/
#21630
b1 *
1/
#21660
0/
#21690
b10 *
1/
#21720
0/
#21750
b11 *
1/
#21780
0/
#21810
b100 *
1/
#21840
0/
#21870
b101 *
1/
#21900
0/
#21930
b110 *
1/
#21960
0/
#21990
b111 *
1/
#22020
0/
#22050
b1000 *
1/
#22080
0/
#22110
0#
b1001 *
1/
#22140
0/
#22170
b1 ,
1#
b0 *
1/
#22200
0/
#22230
b1 *
1/
#22260
0/
#22290
b10 *
1/
#22320
0/
#22350
b11 *
1/
#22380
0/
#22410
b100 *
1/
#22440
0/
#22470
b101 *
1/
#22500
0/
#22530
b110 *
1/
#22560
0/
#22590
b111 *
1/
#22620
0/
#22650
b1000 *
1/
#22680
0/
#22710
0#
b1001 *
1/
#22740
0/
#22770
b10 ,
1#
b0 *
1/
#22800
0/
#22830
b1 *
1/
#22860
0/
#22890
b10 *
1/
#22920
0/
#22950
b11 *
1/
#22980
0/
#23010
b100 *
1/
#23040
0/
#23070
b101 *
1/
#23100
0/
#23130
b110 *
1/
#23160
0/
#23190
b111 *
1/
#23220
0/
#23250
b1000 *
1/
#23280
0/
#23310
0#
b1001 *
1/
#23340
0/
#23370
b11 ,
1#
b0 *
1/
#23400
0/
#23430
b1 *
1/
#23460
0/
#23490
b10 *
1/
#23520
0/
#23550
b11 *
1/
#23580
0/
#23610
b100 *
1/
#23640
0/
#23670
b101 *
1/
#23700
0/
#23730
b110 *
1/
#23760
0/
#23790
b111 *
1/
#23820
0/
#23850
b1000 *
1/
#23880
0/
#23910
0#
b1001 *
1/
#23940
0/
#23970
b100 ,
1#
b0 *
1/
#24000
0/
#24030
b1 *
1/
#24060
0/
#24090
b10 *
1/
#24120
0/
#24150
b11 *
1/
#24180
0/
#24210
b100 *
1/
#24240
0/
#24270
b101 *
1/
#24300
0/
#24330
b110 *
1/
#24360
0/
#24390
b111 *
1/
#24420
0/
#24450
b1000 *
1/
#24480
0/
#24510
0#
b1001 *
1/
#24540
0/
#24570
b101 ,
1#
b0 *
1/
#24600
0/
#24630
b1 *
1/
#24660
0/
#24690
b10 *
1/
#24720
0/
#24750
b11 *
1/
#24780
0/
#24810
b100 *
1/
#24840
0/
#24870
b101 *
1/
#24900
0/
#24930
b110 *
1/
#24960
0/
#24990
b111 *
1/
#25020
0/
#25050
b1000 *
1/
#25080
0/
#25110
0#
b1001 *
1/
#25140
0/
#25170
b111 +
1'
0$
b0 ,
1#
b0 *
1/
#25200
0/
#25230
b1 *
1/
#25260
0/
#25290
b10 *
1/
#25320
0/
#25350
b11 *
1/
#25380
0/
#25410
b100 *
1/
#25440
0/
#25470
b101 *
1/
#25500
0/
#25530
b110 *
1/
#25560
0/
#25590
b111 *
1/
#25620
0/
#25650
b1000 *
1/
#25680
0/
#25710
0#
b1001 *
1/
#25740
0/
#25770
b1 ,
1#
b0 *
1/
#25800
0/
#25830
b1 *
1/
#25860
0/
#25890
b10 *
1/
#25920
0/
#25950
b11 *
1/
#25980
0/
#26010
b100 *
1/
#26040
0/
#26070
b101 *
1/
#26100
0/
#26130
b110 *
1/
#26160
0/
#26190
b111 *
1/
#26220
0/
#26250
b1000 *
1/
#26280
0/
#26310
0#
b1001 *
1/
#26340
0/
#26370
b10 ,
1#
b0 *
1/
#26400
0/
#26430
b1 *
1/
#26460
0/
#26490
b10 *
1/
#26520
0/
#26550
b11 *
1/
#26580
0/
#26610
b100 *
1/
#26640
0/
#26670
b101 *
1/
#26700
0/
#26730
b110 *
1/
#26760
0/
#26790
b111 *
1/
#26820
0/
#26850
b1000 *
1/
#26880
0/
#26910
0#
b1001 *
1/
#26940
0/
#26970
b11 ,
1#
b0 *
1/
#27000
0/
#27030
b1 *
1/
#27060
0/
#27090
b10 *
1/
#27120
0/
#27150
b11 *
1/
#27180
0/
#27210
b100 *
1/
#27240
0/
#27270
b101 *
1/
#27300
0/
#27330
b110 *
1/
#27360
0/
#27390
b111 *
1/
#27420
0/
#27450
b1000 *
1/
#27480
0/
#27510
0#
b1001 *
1/
#27540
0/
#27570
b100 ,
1#
b0 *
1/
#27600
0/
#27630
b1 *
1/
#27660
0/
#27690
b10 *
1/
#27720
0/
#27750
b11 *
1/
#27780
0/
#27810
b100 *
1/
#27840
0/
#27870
b101 *
1/
#27900
0/
#27930
b110 *
1/
#27960
0/
#27990
b111 *
1/
#28020
0/
#28050
b1000 *
1/
#28080
0/
#28110
0#
b1001 *
1/
#28140
0/
#28170
b101 ,
1#
b0 *
1/
#28200
0/
#28230
b1 *
1/
#28260
0/
#28290
b10 *
1/
#28320
0/
#28350
b11 *
1/
#28380
0/
#28410
b100 *
1/
#28440
0/
#28470
b101 *
1/
#28500
0/
#28530
b110 *
1/
#28560
0/
#28590
b111 *
1/
#28620
0/
#28650
b1000 *
1/
#28680
0/
#28710
0#
b1001 *
1/
#28740
0/
#28770
b1000 +
1'
0$
b0 ,
1#
b0 *
1/
#28800
0/
#28830
b1 *
1/
#28860
0/
#28890
b10 *
1/
#28920
0/
#28950
b11 *
1/
#28980
0/
#29010
b100 *
1/
#29040
0/
#29070
b101 *
1/
#29100
0/
#29130
b110 *
1/
#29160
0/
#29190
b111 *
1/
#29220
0/
#29250
b1000 *
1/
#29280
0/
#29310
0#
b1001 *
1/
#29340
0/
#29370
b1 ,
1#
b0 *
1/
#29400
0/
#29430
b1 *
1/
#29460
0/
#29490
b10 *
1/
#29520
0/
#29550
b11 *
1/
#29580
0/
#29610
b100 *
1/
#29640
0/
#29670
b101 *
1/
#29700
0/
#29730
b110 *
1/
#29760
0/
#29790
b111 *
1/
#29820
0/
#29850
b1000 *
1/
#29880
0/
#29910
0#
b1001 *
1/
#29940
0/
#29970
b10 ,
1#
b0 *
1/
#30000
0/
#30030
b1 *
1/
#30060
0/
#30090
b10 *
1/
#30120
0/
#30150
b11 *
1/
#30180
0/
#30210
b100 *
1/
#30240
0/
#30270
b101 *
1/
#30300
0/
#30330
b110 *
1/
#30360
0/
#30390
b111 *
1/
#30420
0/
#30450
b1000 *
1/
#30480
0/
#30510
0#
b1001 *
1/
#30540
0/
#30570
b11 ,
1#
b0 *
1/
#30600
0/
#30630
b1 *
1/
#30660
0/
#30690
b10 *
1/
#30720
0/
#30750
b11 *
1/
#30780
0/
#30810
b100 *
1/
#30840
0/
#30870
b101 *
1/
#30900
0/
#30930
b110 *
1/
#30960
0/
#30990
b111 *
1/
#31020
0/
#31050
b1000 *
1/
#31080
0/
#31110
0#
b1001 *
1/
#31140
0/
#31170
b100 ,
1#
b0 *
1/
#31200
0/
#31230
b1 *
1/
#31260
0/
#31290
b10 *
1/
#31320
0/
#31350
b11 *
1/
#31380
0/
#31410
b100 *
1/
#31440
0/
#31470
b101 *
1/
#31500
0/
#31530
b110 *
1/
#31560
0/
#31590
b111 *
1/
#31620
0/
#31650
b1000 *
1/
#31680
0/
#31710
0#
b1001 *
1/
#31740
0/
#31770
b101 ,
1#
b0 *
1/
#31800
0/
#31830
b1 *
1/
#31860
0/
#31890
b10 *
1/
#31920
0/
#31950
b11 *
1/
#31980
0/
#32010
b100 *
1/
#32040
0/
#32070
b101 *
1/
#32100
0/
#32130
b110 *
1/
#32160
0/
#32190
b111 *
1/
#32220
0/
#32250
b1000 *
1/
#32280
0/
#32310
0#
b1001 *
1/
#32340
0/
#32370
0!
b1001 +
1'
0$
b0 ,
1#
b0 *
1/
#32400
0/
#32430
b1 *
1/
#32460
0/
#32490
b10 *
1/
#32520
0/
#32550
b11 *
1/
#32580
0/
#32610
b100 *
1/
#32640
0/
#32670
b101 *
1/
#32700
0/
#32730
b110 *
1/
#32760
0/
#32790
b111 *
1/
#32820
0/
#32850
b1000 *
1/
#32880
0/
#32910
0#
b1001 *
1/
#32940
0/
#32970
b1 ,
1#
b0 *
1/
#33000
0/
#33030
b1 *
1/
#33060
0/
#33090
b10 *
1/
#33120
0/
#33150
b11 *
1/
#33180
0/
#33210
b100 *
1/
#33240
0/
#33270
b101 *
1/
#33300
0/
#33330
b110 *
1/
#33360
0/
#33390
b111 *
1/
#33420
0/
#33450
b1000 *
1/
#33480
0/
#33510
0#
b1001 *
1/
#33540
0/
#33570
b10 ,
1#
b0 *
1/
#33600
0/
#33630
b1 *
1/
#33660
0/
#33690
b10 *
1/
#33720
0/
#33750
b11 *
1/
#33780
0/
#33810
b100 *
1/
#33840
0/
#33870
b101 *
1/
#33900
0/
#33930
b110 *
1/
#33960
0/
#33990
b111 *
1/
#34020
0/
#34050
b1000 *
1/
#34080
0/
#34110
0#
b1001 *
1/
#34140
0/
#34170
b11 ,
1#
b0 *
1/
#34200
0/
#34230
b1 *
1/
#34260
0/
#34290
b10 *
1/
#34320
0/
#34350
b11 *
1/
#34380
0/
#34410
b100 *
1/
#34440
0/
#34470
b101 *
1/
#34500
0/
#34530
b110 *
1/
#34560
0/
#34590
b111 *
1/
#34620
0/
#34650
b1000 *
1/
#34680
0/
#34710
0#
b1001 *
1/
#34740
0/
#34770
b100 ,
1#
b0 *
1/
#34800
0/
#34830
b1 *
1/
#34860
0/
#34890
b10 *
1/
#34920
0/
#34950
b11 *
1/
#34980
0/
#35010
b100 *
1/
#35040
0/
#35070
b101 *
1/
#35100
0/
#35130
b110 *
1/
#35160
0/
#35190
b111 *
1/
#35220
0/
#35250
b1000 *
1/
#35280
0/
#35310
0#
b1001 *
1/
#35340
0/
#35370
b101 ,
1#
b0 *
1/
#35400
0/
#35430
b1 *
1/
#35460
0/
#35490
b10 *
1/
#35520
0/
#35550
b11 *
1/
#35580
0/
#35610
b100 *
1/
#35640
0/
#35670
b101 *
1/
#35700
0/
#35730
b110 *
1/
#35760
0/
#35790
b111 *
1/
#35820
0/
#35850
b1000 *
1/
#35880
0/
#35910
0#
b1001 *
1/
#35940
0/
#35970
b1 -
1!
b0 +
1'
0$
b0 ,
1#
b0 *
1/
#36000
0/
#36030
b1 *
1/
#36060
0/
#36090
b10 *
1/
#36120
0/
#36150
b11 *
1/
#36180
0/
#36210
b100 *
1/
#36240
0/
#36270
b101 *
1/
#36300
0/
#36330
b110 *
1/
#36360
0/
#36390
b111 *
1/
#36420
0/
#36450
b1000 *
1/
#36480
0/
#36510
0#
b1001 *
1/
#36540
0/
#36570
b1 ,
1#
b0 *
1/
#36600
0/
#36630
b1 *
1/
#36660
0/
#36690
b10 *
1/
#36720
0/
#36750
b11 *
1/
#36780
0/
#36810
b100 *
1/
#36840
0/
#36870
b101 *
1/
#36900
0/
#36930
b110 *
1/
#36960
0/
#36990
b111 *
1/
#37020
0/
#37050
b1000 *
1/
#37080
0/
#37110
0#
b1001 *
1/
#37140
0/
#37170
b10 ,
1#
b0 *
1/
#37200
0/
#37230
b1 *
1/
#37260
0/
#37290
b10 *
1/
#37320
0/
#37350
b11 *
1/
#37380
0/
#37410
b100 *
1/
#37440
0/
#37470
b101 *
1/
#37500
0/
#37530
b110 *
1/
#37560
0/
#37590
b111 *
1/
#37620
0/
#37650
b1000 *
1/
#37680
0/
#37710
0#
b1001 *
1/
#37740
0/
#37770
b11 ,
1#
b0 *
1/
#37800
0/
#37830
b1 *
1/
#37860
0/
#37890
b10 *
1/
#37920
0/
#37950
b11 *
1/
#37980
0/
#38010
b100 *
1/
#38040
0/
#38070
b101 *
1/
#38100
0/
#38130
b110 *
1/
#38160
0/
#38190
b111 *
1/
#38220
0/
#38250
b1000 *
1/
#38280
0/
#38310
0#
b1001 *
1/
#38340
0/
#38370
b100 ,
1#
b0 *
1/
#38400
0/
#38430
b1 *
1/
#38460
0/
#38490
b10 *
1/
#38520
0/
#38550
b11 *
1/
#38580
0/
#38610
b100 *
1/
#38640
0/
#38670
b101 *
1/
#38700
0/
#38730
b110 *
1/
#38760
0/
#38790
b111 *
1/
#38820
0/
#38850
b1000 *
1/
#38880
0/
#38910
0#
b1001 *
1/
#38940
0/
#38970
b101 ,
1#
b0 *
1/
#39000
0/
#39030
b1 *
1/
#39060
0/
#39090
b10 *
1/
#39120
0/
#39150
b11 *
1/
#39180
0/
#39210
b100 *
1/
#39240
0/
#39270
b101 *
1/
#39300
0/
