ContadorMod10/resetasync/design.sv
module Contador(clk,reset,q);
    input clk;
    input reset;
    output reg [3:0] q;

    initial
        q <= 4'b0000;

    always @(posedge clk, posedge reset) begin
        if(!reset)
            if (q >= 4'b1001)
                q <= 4'b0000;
            else
                q <= q + 1;
        else
            q <= 4'b0000;
    end

endmodule

ContadorMod10/resetasync/testbench.v
module test;

    reg  clk, r;
    wire [3:0] q;

    Contador CONTADOR(.clk(clk),
          .reset(r),
          .q(q));

    initial begin
        $dumpfile("dump.vcd");
        $dumpvars(1,test);

        clk = 0;
        r = 0;

        #130 reset;

    end

    always
    begin
       #5 clk = ~clk;
       #5 clk = ~clk;
    end

    task reset;
        begin
            #1 r = ~r;
            #1 r = ~r;
        end
    endtask

    initial
        #200 $finish;

endmodule

ContadorMod10/resetasync/dump.vcd
$date
	Mon Mar 16 09:16:48 2020
$end
$version
	Icarus Verilog
$end
$timescale
	1s
$end
$scope module test $end
$var wire 4 ! q [3:0] $end
$var reg 1 " clk $end
$var reg 1 # r $end
$upscope $end
$enddefinitions $end
#0
$dumpvars
0#
0"
b0 !
$end
#5
b1 !
1"
#10
0"
#15
b10 !
1"
#20
0"
#25
b11 !
1"
#30
0"
#35
b100 !
1"
#40
0"
#45
b101 !
1"
#50
0"
#55
b110 !
1"
#60
0"
#65
b111 !
1"
#70
0"
#75
b1000 !
1"
#80
0"
#85
b1001 !
1"
#90
0"
#95
b0 !
1"
#100
0"
#105
b1 !
1"
#110
0"
#115
b10 !
1"
#120
0"
#125
b11 !
1"
#130
0"
#131
b0 !
1#
#132
0#
#135
b1 !
1"
#140
0"
#145
b10 !
1"
#150
0"
#155
b11 !
1"
#160
0"
#165
b100 !
1"
#170
0"
#175
b101 !
1"
#180
0"
#185
b110 !
1"
#190
0"
#195
b111 !
1"
