ContadorMod10/resetsync/design.sv
module Contador(clk,reset,q);
    input clk;
    input reset;
    output reg [3:0] q;

    initial
    q <= 4'b0000;

    always @(posedge clk) begin
        if (!reset)
            if (q >= 4'b1001)
                q <= 4'b0000;
            else
                q <= q + 1;
        else
            q <= 4'b0000;
    end
endmodule

ContadorMod10/resetsync/testbench.sv
module test;

    reg  clk, r;
    wire [3:0] q;

    // Instantiate device under test
    Contador CONTADOR(.clk(clk),
          .reset(r),
          .q(q));

    initial begin
        // Dump waves
        $dumpfile("dump.vcd");
        $dumpvars(1,test);

        clk = 0;
        r = 0;

        #130 r = 1;

    end

    always
    begin
       #5 clk = ~clk;
       #5 clk = ~clk;
    end

    initial
        #200 $finish;

endmodule

ContadorMod10/dump.vcd
$date
	Sun Mar 15 22:22:02 2020
$end
$version
	Icarus Verilog
$end
$timescale
	1s
$end
$scope module test $end
$var wire 4 ! q [3:0] $end
$var reg 1 " clk $end
$var reg 1 # r $end
$upscope $end
$enddefinitions $end
#0
$dumpvars
0#
0"
b0 !
$end
#5
b1 !
1"
#10
0"
#15
b10 !
1"
#20
0"
#25
b11 !
1"
#30
0"
#35
b100 !
1"
#40
0"
#45
b101 !
1"
#50
0"
#55
b110 !
1"
#60
0"
#65
b111 !
1"
#70
0"
#75
b1000 !
1"
#80
0"
#85
b1001 !
1"
#90
0"
#95
b0 !
1"
#100
0"
#105
b1 !
1"
#110
0"
#115
b10 !
1"
#120
0"
#125
b11 !
1"
#130
0"
1#
#135
b0 !
1"
